[
{"#":"int32","Name":"str","Icon":"Image","Category":"byte","Order":"byte","ClassJob":"ClassJob"},
{"#":"0","Name":"","Icon":"0","Category":"0","Order":"0","ClassJob":"0"},
{"#":"1","Name":"Primary Arms","Icon":"60102","Category":"0","Order":"0","ClassJob":"0"},
{"#":"2","Name":"Primary Tools","Icon":"60113","Category":"0","Order":"0","ClassJob":"0"},
{"#":"3","Name":"Primary Tools","Icon":"60120","Category":"0","Order":"0","ClassJob":"0"},
{"#":"4","Name":"Armor","Icon":"60126","Category":"0","Order":"0","ClassJob":"0"},
{"#":"5","Name":"Accessories","Icon":"60135","Category":"0","Order":"0","ClassJob":"0"},
{"#":"6","Name":"Medicines","Icon":"60136","Category":"0","Order":"0","ClassJob":"0"},
{"#":"7","Name":"Materials","Icon":"60137","Category":"0","Order":"0","ClassJob":"0"},
{"#":"8","Name":"Other","Icon":"60159","Category":"0","Order":"0","ClassJob":"0"},
{"#":"9","Name":"Pugilist's Arms","Icon":"60101","Category":"1","Order":"4","ClassJob":"2"},
{"#":"10","Name":"Gladiator's Arms","Icon":"60102","Category":"1","Order":"0","ClassJob":"1"},
{"#":"11","Name":"Marauder's Arms","Icon":"60103","Category":"1","Order":"1","ClassJob":"3"},
{"#":"12","Name":"Archer's Arms","Icon":"60105","Category":"1","Order":"7","ClassJob":"5"},
{"#":"13","Name":"Lancer's Arms","Icon":"60104","Category":"1","Order":"3","ClassJob":"4"},
{"#":"14","Name":"Thaumaturge's Arms","Icon":"60108","Category":"1","Order":"9","ClassJob":"7"},
{"#":"15","Name":"Conjurer's Arms","Icon":"60107","Category":"1","Order":"12","ClassJob":"6"},
{"#":"16","Name":"Arcanist's Arms","Icon":"60109","Category":"1","Order":"10","ClassJob":"26"},
{"#":"17","Name":"Shields","Icon":"60110","Category":"2","Order":"0","ClassJob":"0"},
{"#":"18","Name":"Throwing Weapons","Icon":"60111","Category":"0","Order":"0","ClassJob":"0"},
{"#":"19","Name":"Carpenter's Tools","Icon":"60112","Category":"1","Order":"15","ClassJob":"8"},
{"#":"20","Name":"Blacksmith's Tools","Icon":"60113","Category":"1","Order":"16","ClassJob":"9"},
{"#":"21","Name":"Armorer's Tools","Icon":"60114","Category":"1","Order":"17","ClassJob":"10"},
{"#":"22","Name":"Goldsmith's Tools","Icon":"60115","Category":"1","Order":"18","ClassJob":"11"},
{"#":"23","Name":"Leatherworker's Tools","Icon":"60116","Category":"1","Order":"19","ClassJob":"12"},
{"#":"24","Name":"Weaver's Tools","Icon":"60117","Category":"1","Order":"20","ClassJob":"13"},
{"#":"25","Name":"Alchemist's Tools","Icon":"60118","Category":"1","Order":"21","ClassJob":"14"},
{"#":"26","Name":"Culinarian's Tools","Icon":"60119","Category":"1","Order":"22","ClassJob":"15"},
{"#":"27","Name":"Miner's Tools","Icon":"60120","Category":"1","Order":"23","ClassJob":"16"},
{"#":"28","Name":"Botanist's Tools","Icon":"60121","Category":"1","Order":"24","ClassJob":"17"},
{"#":"29","Name":"Fisher's Tools","Icon":"60122","Category":"1","Order":"25","ClassJob":"18"},
{"#":"30","Name":"Fishing Tackle","Icon":"60123","Category":"1","Order":"26","ClassJob":"18"},
{"#":"31","Name":"Head","Icon":"60124","Category":"2","Order":"1","ClassJob":"0"},
{"#":"32","Name":"Undershirts","Icon":"60125","Category":"0","Order":"0","ClassJob":"0"},
{"#":"33","Name":"Body","Icon":"60126","Category":"2","Order":"2","ClassJob":"0"},
{"#":"34","Name":"Undergarments","Icon":"60127","Category":"0","Order":"0","ClassJob":"0"},
{"#":"35","Name":"Legs","Icon":"60128","Category":"2","Order":"5","ClassJob":"0"},
{"#":"36","Name":"Hands","Icon":"60129","Category":"2","Order":"3","ClassJob":"0"},
{"#":"37","Name":"Feet","Icon":"60130","Category":"2","Order":"6","ClassJob":"0"},
{"#":"38","Name":"Waist","Icon":"60131","Category":"2","Order":"4","ClassJob":"0"},
{"#":"39","Name":"Necklaces","Icon":"60132","Category":"2","Order":"9","ClassJob":"0"},
{"#":"40","Name":"Earrings","Icon":"60133","Category":"2","Order":"8","ClassJob":"0"},
{"#":"41","Name":"Bracelets","Icon":"60134","Category":"2","Order":"10","ClassJob":"0"},
{"#":"42","Name":"Rings","Icon":"60135","Category":"2","Order":"11","ClassJob":"0"},
{"#":"43","Name":"Medicine","Icon":"60136","Category":"3","Order":"0","ClassJob":"0"},
{"#":"44","Name":"Ingredients","Icon":"60137","Category":"3","Order":"1","ClassJob":"0"},
{"#":"45","Name":"Meals","Icon":"60146","Category":"3","Order":"2","ClassJob":"0"},
{"#":"46","Name":"Seafood","Icon":"60138","Category":"3","Order":"3","ClassJob":"0"},
{"#":"47","Name":"Stone","Icon":"60139","Category":"3","Order":"4","ClassJob":"0"},
{"#":"48","Name":"Metal","Icon":"60140","Category":"3","Order":"5","ClassJob":"0"},
{"#":"49","Name":"Lumber","Icon":"60141","Category":"3","Order":"6","ClassJob":"0"},
{"#":"50","Name":"Cloth","Icon":"60142","Category":"3","Order":"7","ClassJob":"0"},
{"#":"51","Name":"Leather","Icon":"60143","Category":"3","Order":"8","ClassJob":"0"},
{"#":"52","Name":"Bone","Icon":"60144","Category":"3","Order":"9","ClassJob":"0"},
{"#":"53","Name":"Reagents","Icon":"60145","Category":"3","Order":"10","ClassJob":"0"},
{"#":"54","Name":"Dyes","Icon":"60147","Category":"3","Order":"11","ClassJob":"0"},
{"#":"55","Name":"Weapon Parts","Icon":"60148","Category":"3","Order":"12","ClassJob":"0"},
{"#":"56","Name":"Furnishings","Icon":"60164","Category":"4","Order":"3","ClassJob":"0"},
{"#":"57","Name":"Materia","Icon":"60150","Category":"3","Order":"13","ClassJob":"0"},
{"#":"58","Name":"Crystals","Icon":"60151","Category":"3","Order":"14","ClassJob":"0"},
{"#":"59","Name":"Catalysts","Icon":"60152","Category":"3","Order":"15","ClassJob":"0"},
{"#":"60","Name":"Miscellany","Icon":"60153","Category":"3","Order":"16","ClassJob":"0"},
{"#":"61","Name":"Soul Crystals","Icon":"60157","Category":"0","Order":"0","ClassJob":"0"},
{"#":"62","Name":"Arrows","Icon":"60153","Category":"0","Order":"0","ClassJob":"0"},
{"#":"63","Name":"Quest Items","Icon":"60158","Category":"0","Order":"0","ClassJob":"0"},
{"#":"64","Name":"Other","Icon":"60159","Category":"0","Order":"0","ClassJob":"0"},
{"#":"65","Name":"Exterior Fixtures","Icon":"60160","Category":"4","Order":"0","ClassJob":"0"},
{"#":"66","Name":"Interior Fixtures","Icon":"60161","Category":"4","Order":"1","ClassJob":"0"},
{"#":"67","Name":"Outdoor Furnishings","Icon":"60168","Category":"4","Order":"2","ClassJob":"0"},
{"#":"68","Name":"Chairs and Beds","Icon":"60165","Category":"4","Order":"4","ClassJob":"0"},
{"#":"69","Name":"Tables","Icon":"60162","Category":"4","Order":"5","ClassJob":"0"},
{"#":"70","Name":"Tabletop","Icon":"60163","Category":"4","Order":"6","ClassJob":"0"},
{"#":"71","Name":"Wall-mounted","Icon":"60166","Category":"4","Order":"7","ClassJob":"0"},
{"#":"72","Name":"Rugs","Icon":"60167","Category":"4","Order":"8","ClassJob":"0"},
{"#":"73","Name":"Rogue's Arms","Icon":"60106","Category":"1","Order":"6","ClassJob":"29"},
{"#":"74","Name":"Seasonal Miscellany","Icon":"60154","Category":"3","Order":"17","ClassJob":"0"},
{"#":"75","Name":"Minions","Icon":"60155","Category":"3","Order":"18","ClassJob":"0"},
{"#":"76","Name":"Dark Knight's Arms","Icon":"60170","Category":"1","Order":"2","ClassJob":"32"},
{"#":"77","Name":"Machinist's Arms","Icon":"60172","Category":"1","Order":"8","ClassJob":"31"},
{"#":"78","Name":"Astrologian's Arms","Icon":"60171","Category":"1","Order":"14","ClassJob":"33"},
{"#":"79","Name":"Airship/Submersible Components","Icon":"60169","Category":"3","Order":"19","ClassJob":"0"},
{"#":"80","Name":"Orchestrion Components","Icon":"60173","Category":"3","Order":"20","ClassJob":"0"},
{"#":"81","Name":"Gardening Items","Icon":"60174","Category":"4","Order":"9","ClassJob":"0"},
{"#":"82","Name":"Paintings","Icon":"60175","Category":"4","Order":"10","ClassJob":"0"},
{"#":"83","Name":"Samurai's Arms","Icon":"60177","Category":"1","Order":"5","ClassJob":"34"},
{"#":"84","Name":"Red Mage's Arms","Icon":"60176","Category":"1","Order":"11","ClassJob":"35"},
{"#":"85","Name":"Scholar's Arms","Icon":"60178","Category":"1","Order":"13","ClassJob":"28"},
{"#":"86","Name":"","Icon":"0","Category":"0","Order":"0","ClassJob":"0"},
{"#":"87","Name":"","Icon":"0","Category":"0","Order":"0","ClassJob":"0"},
{"#":"88","Name":"","Icon":"0","Category":"0","Order":"0","ClassJob":"0"},
{"#":"89","Name":"","Icon":"0","Category":"0","Order":"0","ClassJob":"0"},
{"#":"90","Name":"","Icon":"0","Category":"0","Order":"0","ClassJob":"0"},
{"#":"91","Name":"","Icon":"0","Category":"0","Order":"0","ClassJob":"0"},
{"#":"92","Name":"","Icon":"0","Category":"0","Order":"0","ClassJob":"0"},
{"#":"93","Name":"","Icon":"0","Category":"0","Order":"0","ClassJob":"0"},
{"#":"94","Name":"","Icon":"0","Category":"0","Order":"0","ClassJob":"0"},
{"#":"95","Name":"","Icon":"0","Category":"0","Order":"0","ClassJob":"0"},
{"#":"96","Name":"","Icon":"0","Category":"0","Order":"0","ClassJob":"0"},
{"#":"97","Name":"","Icon":"0","Category":"0","Order":"0","ClassJob":"0"},
{"#":"98","Name":"","Icon":"0","Category":"0","Order":"0","ClassJob":"0"},
{"#":"99","Name":"","Icon":"0","Category":"0","Order":"0","ClassJob":"0"},
{"#":"100","Name":"","Icon":"0","Category":"0","Order":"0","ClassJob":"0"}
]